LICENSE
MANIFEST.in
README.md
setup.cfg
setup.py
markdown_slides.egg-info/PKG-INFO
markdown_slides.egg-info/SOURCES.txt
markdown_slides.egg-info/dependency_links.txt
markdown_slides.egg-info/entry_points.txt
markdown_slides.egg-info/requires.txt
markdown_slides.egg-info/top_level.txt
slides/__init__.py
slides/__main__.py
slides/frontmatter.schema.yaml
slides/util.py
slides/demo/README.md
slides/demo/figure.png
slides/static/css/harvard.css
slides/static/css/slides.css
slides/templates/index.html
slides/templates/slides.html
tests/test_util.py