Metadata-Version: 2.1
Name: markdown-slides
Version: 0.1.11
License-File: LICENSE
